nb2pb-0.1.14.dist-info/METADATA
nb2pb-0.1.14.dist-info/WHEEL
nb2pb-0.1.14.dist-info/licenses/LICENSE-APACHE.txt
nb2pb-0.1.14.dist-info/licenses/LICENSE-MIT.txt
nb2pb/__init__.py
nb2pb/nb2pb.cpython-313-darwin.so
nb2pb-0.1.14.dist-info/RECORD
