Metadata-Version: 2.3
Name: nb2pb
Version: 0.1.14
Classifier: Development Status :: 1 - Planning
Classifier: Intended Audience :: Developers
Classifier: Programming Language :: Rust
Classifier: Programming Language :: Python :: 3 :: Only
Classifier: Programming Language :: Python :: Implementation :: CPython
Classifier: Programming Language :: Python :: Implementation :: PyPy
Classifier: Topic :: Software Development :: Code Generators
Classifier: Topic :: Software Development :: Compilers
Requires-Dist: cffi
License-File: LICENSE-APACHE.txt
License-File: LICENSE-MIT.txt
Summary: Compiles NetsBlox projects into PyBlox projects
